{
    "coordinates": {
        "time": {
            "axis": "T",
            "bounds": "time_bnds",
            "calendar": "noleap",
            "id": "time",
            "length": 1140,
            "long_name": "time",
            "max": "2100-12-16T12:00:00",
            "min": "2006-01-16T12:00:00",
            "standard_name": "time"
        }
    },
    "data": {
        "coord_names": [
            "time"
        ],
        "max": null,
        "min": null,
        "rank": 1,
        "shape": [
            1140
        ]
    },
    "global_attrs": {
        "Conventions": "CF-1.4",
        "acknowledgements": "The CESM project is supported by the National Science Foundation and the Office of Science (BER) of the U.S. Department of Energy. NCAR is sponsored by the National Science Foundation. Computing resources were provided by the Climate Simulation Laboratory at the NCAR Computational and Information Systems Laboratory (CISL), sponsored by the National Science Foundation and other agencies.",
        "branch_time": 20.0,
        "cesm_casename": "b40.rcp4_5.1deg.001",
        "cesm_compset": "BRCP45CN",
        "cesm_repotag": "ccsm4_0_beta49",
        "cmor_version": "2.8.1",
        "comment": "CESM home page: http://www.cesm.ucar.edu",
        "contact": "cesm_data@ucar.edu",
        "creation_date": "2012-09-14T22:19:32Z",
        "experiment": "RCP4.5",
        "experiment_id": "rcp45",
        "forcing": "Sl GHG SS Ds SA BC MD OC Oz AA",
        "forcing_note": "Additional information on the external forcings used in this experiment can be found at http://www.cesm.ucar.edu/CMIP5/forcing_information",
        "frequency": "mon",
        "history": "2012-09-14T22:19:32Z CMOR rewrote data to comply with CF standards and CMIP5 requirements.",
        "initialization_method": 1,
        "institute_id": "NCAR",
        "institution": "NCAR (National Center for Atmospheric Research) Boulder, CO, USA",
        "model_id": "CCSM4",
        "modeling_realm": "ocean",
        "parent_experiment": "historical",
        "parent_experiment_id": "historical",
        "parent_experiment_rip": "r1i1p1",
        "physics_version": 1,
        "processed_by": "strandwg on silver.cgd.ucar.edu at 20120914  -161932.667",
        "processing_code_information": "Last Changed Rev: 1044 Last Changed Date: 2012-09-06 09:58:22 -0600 (Thu, 06 Sep 2012) Repository UUID: d2181dbe-5796-6825-dc7f-cbd98591f93d",
        "product": "output",
        "project_id": "CMIP5",
        "realization": 1,
        "references": "Gent P. R., et.al. 2011: The Community Climate System Model version 4. J. Climate, doi: 10.1175/2011JCLI4083.1",
        "resolution": "f09_g16 (0.9x1.25_gx1v6)",
        "source": "CCSM4",
        "table_id": "Table Omon (12 January 2012) 4c362966a7f18e92386a2236c2fad543",
        "title": "CCSM4 model output prepared for CMIP5 RCP4.5",
        "tracking_id": "b39d2dde-0cc8-4bd7-8983-fed5f5dc188e"
    },
    "scan_metadata": {
        "last_scanned": "2020-04-02T15:23:57.023480",
        "location": "ceda",
        "mode": "quick"
    },
    "variable": {
        "_FillValue": "1e+20",
        "associated_files": "baseURL: http://cmip-pcmdi.llnl.gov/CMIP5/dataLocation gridspecFile: gridspec_ocean_fx_CCSM4_rcp45_r0i0p0.nc",
        "cell_methods": "time: mean (interval: 30 days) area: mean where sea",
        "comment": "ave_slc_t from Aixue's SLC code; derived from SSH PD TEMP SALT",
        "history": "2012-09-14T22:19:32Z altered by CMOR: Converted units from 'cm' to 'm'. 2012-09-14T22:19:32Z altered by CMOR: replaced missing value flag (-1e+34) with standard missing value (1e+20).",
        "long_name": "Global Average Thermosteric Sea Level Change",
        "original_name": "ave_slc_t",
        "original_units": "cm",
        "standard_name": "global_average_thermosteric_sea_level_change",
        "units": "m",
        "var_id": "zostoga"
    }
}